larc/__init__.py
larc/common.py
larc/logging.py
larc/parallel.py
larc/rest.py
larc/shell.py
larc/signature.py
larc/ssh.py
larc/yaml.py
larc/cli/__init__.py
larc/cli/common.py
larc/cli/ips.py
larc/cli/text.py
larc/graph/__init__.py
larc/graph/common.py
larc/graph/network.py
larc/images/__init__.py
larc/images/common.py
larc/markdown/__init__.py
larc/markdown/card.py
larc/markdown/image_fig.py
larc/markdown/meta_yaml.py
larc/markdown/table.py
larc/markdown/yaml_data.py
larc/templates/__init__.py
larc/templates/common.py
larc-0.0.27.dist-info/LICENSE
larc-0.0.27.dist-info/METADATA
larc-0.0.27.dist-info/WHEEL
larc-0.0.27.dist-info/entry_points.txt
larc-0.0.27.dist-info/top_level.txt
larc-0.0.27.dist-info/RECORD
