Metadata-Version: 2.1
Name: larc
Version: 0.0.27
Summary: Collection of helper functions and general utilities used across various LARC projects
Home-page: https://github.com/lowlandresearch/larc
Author: Lowland Applied Research Company (LARC)
Author-email: dogwynn@lowlandresearch.com
License: MIT
Keywords: utilities functional toolz
Platform: UNKNOWN
Classifier: Development Status :: 3 - Alpha
Classifier: Intended Audience :: Developers
Classifier: License :: OSI Approved :: MIT License
Classifier: Programming Language :: Python :: 3.7
Requires-Dist: toolz
Requires-Dist: multipledispatch
Requires-Dist: pyrsistent
Requires-Dist: networkx
Requires-Dist: coloredlogs
Requires-Dist: gevent
Requires-Dist: ruamel.yaml
Requires-Dist: ipython
Requires-Dist: click
Requires-Dist: pyperclip
Requires-Dist: python-nmap
Requires-Dist: tcping
Requires-Dist: ipparser
Requires-Dist: dnspython
Requires-Dist: paramiko
Requires-Dist: xmljson
Requires-Dist: python-dateutil
Requires-Dist: jmespath
Requires-Dist: ifcfg
Requires-Dist: markdown
Requires-Dist: jinja2
Requires-Dist: pillow
